IndiAvesBirdIdentification/__init__.py
IndiAvesBirdIdentification/bird_detection.py
IndiAvesBirdIdentification/exim.py
IndiAvesBirdIdentification/get_bird_names.py
IndiAvesBirdIdentification/preprocess.py
IndiAvesBirdIdentification/files/all_birds_list
IndiAvesBirdIdentification/files/birdnames_words
IndiAvesBirdIdentification/model-best/.DS_Store
IndiAvesBirdIdentification/model-best/config.cfg
IndiAvesBirdIdentification/model-best/meta.json
IndiAvesBirdIdentification/model-best/tokenizer
IndiAvesBirdIdentification/model-best/ner/cfg
IndiAvesBirdIdentification/model-best/ner/model
IndiAvesBirdIdentification/model-best/ner/moves
IndiAvesBirdIdentification/model-best/tok2vec/cfg
IndiAvesBirdIdentification/model-best/tok2vec/model
IndiAvesBirdIdentification/model-best/vocab/key2row
IndiAvesBirdIdentification/model-best/vocab/lookups.bin
IndiAvesBirdIdentification/model-best/vocab/strings.json
IndiAvesBirdIdentification/model-best/vocab/vectors
IndiAvesBirdIdentification/model-best/vocab/vectors.cfg
IndiAvesBirdIdentification_ASaha-1.2.dist-info/METADATA
IndiAvesBirdIdentification_ASaha-1.2.dist-info/WHEEL
IndiAvesBirdIdentification_ASaha-1.2.dist-info/top_level.txt
IndiAvesBirdIdentification_ASaha-1.2.dist-info/RECORD
